zipfix/__init__.py
zipfix/merge.py
zipfix/odb.py
zipfix-0.1.data/scripts/git-zipfix
zipfix-0.1.dist-info/DESCRIPTION.rst
zipfix-0.1.dist-info/METADATA
zipfix-0.1.dist-info/RECORD
zipfix-0.1.dist-info/WHEEL
zipfix-0.1.dist-info/metadata.json
zipfix-0.1.dist-info/top_level.txt
